moojoco_env/__init__.py
moojoco_env/environment/__init__.py
moojoco_env/environment/base.py
moojoco_env/environment/dual.py
moojoco_env/environment/mjc_env.py
moojoco_env/environment/mjx_env.py
moojoco_env/environment/mjx_spaces.py
moojoco_env/environment/renderer.py
moojoco_env/mjcf/__init__.py
moojoco_env/mjcf/arena.py
moojoco_env/mjcf/component.py
moojoco_env/mjcf/morphology.py
moojoco_env-1.0.2.dist-info/LICENSE
moojoco_env-1.0.2.dist-info/METADATA
moojoco_env-1.0.2.dist-info/WHEEL
moojoco_env-1.0.2.dist-info/top_level.txt
moojoco_env-1.0.2.dist-info/RECORD
