Metadata-Version: 2.1
Name: moojoco-env
Version: 1.0.2
Summary: A unified framework for implementing and interfacing with MuJoCo and MuJoCo-XLA simulation environments.
Home-page: https://github.com/Co-Evolve/moojoco-env
Author-email: Dries Marzougui <dries.marzougui@gmail.com>
License: MIT
Project-URL: Homepage, https://github.com/Co-Evolve/moojoco-env
Project-URL: Repository, https://github.com/Co-Evolve/moojoco-env
Classifier: Development Status :: 5 - Production/Stable
Classifier: Intended Audience :: Developers
Classifier: Intended Audience :: Science/Research
Classifier: Natural Language :: English
Classifier: Programming Language :: Python :: 3
Classifier: Programming Language :: Python :: 3.8
Classifier: Programming Language :: Python :: 3.9
Classifier: Programming Language :: Python :: 3.10
Classifier: Programming Language :: Python :: 3.11
Classifier: Programming Language :: Python :: 3.12
Classifier: Topic :: Scientific/Engineering
Requires-Python: >=3.8
License-File: LICENSE
Requires-Dist: chex
Requires-Dist: dm-control
Requires-Dist: flax
Requires-Dist: fprs
Requires-Dist: glfw
Requires-Dist: gymnasium
Requires-Dist: imageio
Requires-Dist: mujoco
Requires-Dist: mujoco-mjx
Requires-Dist: numpy
Requires-Dist: scipy
